[
  {
    "key": "0-place",
    "original": "蒼白な鯨の体内\n<CMT_KR>\n<CMT_JP>",
    "translation": "蒼白な鯨の体内\n<CMT_KR>\n<CMT_JP>",
    "stage": 1,
    "context": "KR:\n창백한 고래의 몸 속\nEN:\nInside the Pallid Whale"
  },
  {
    "key": "0-content",
    "original": "全員！目を大きくかっ開いて\nボートを探すことに専念するように。\n<CMT_KR>\n<CMT_JP>",
    "translation": "全員！目を大きくかっ開いて\nボートを探すことに専念するように。\n<CMT_KR>\n<CMT_JP>",
    "stage": 1,
    "context": "KR:\n전원! 눈을 크게 뜨고 보트를 찾는 데에 전념하도록.\nEN:\nMen! We will commence a search. This boat must be found as soon as possible."
  },
  {
    "key": "1-content",
    "original": "いや、目は大きく開かなくとも問題ない。\n<CMT_KR>\n<CMT_JP>",
    "translation": "いや、目は大きく開かなくとも問題ない。\n<CMT_KR>\n<CMT_JP>",
    "stage": 1,
    "context": "KR:\n아니, 눈은 크게 뜨지 않아도 된다.\nEN:\nNo, there is no need for a search."
  },
  {
    "key": "2-content",
    "original": "右側、約400m先に見える。\nそこに私たちの乗ってきた舟が…。\n<CMT_KR>\n<CMT_JP>",
    "translation": "右側、約400m先に見える。\nそこに私たちの乗ってきた舟が…。\n<CMT_KR>\n<CMT_JP>",
    "stage": 1,
    "context": "KR:\n오른쪽, 400m 즈음에 보인다. 그곳에 우리가 타고 온 배가…\nEN:\n400 meters to your right. There is the boat—"
  },
  {
    "key": "3-content",
    "original": "悪くない観察力だな。今すぐに移動しよう。\n<CMT_KR>\n<CMT_JP>",
    "translation": "悪くない観察力だな。今すぐに移動しよう。\n<CMT_KR>\n<CMT_JP>",
    "stage": 1,
    "context": "KR:\n나쁘지 않은 관찰력이군. 곧바로 이동하지.\nEN:\nQuite observant you are. Let's not waste any time and return to the boat."
  },
  {
    "key": "4-content",
    "original": "最後まで聞く必要がある。\n舟の75%以上が破損した状態で散らばり、床に突き刺さっている。\n<CMT_KR>\n<CMT_JP>",
    "translation": "最後まで聞く必要がある。\n舟の75%以上が破損した状態で散らばり、床に突き刺さっている。\n<CMT_KR>\n<CMT_JP>",
    "stage": 1,
    "context": "KR:\n마지막까지 들어야 한다. 배의 75% 이상이 파손된 채로 흩어져 바닥에 처박혀 있다.\nEN:\nAllow me to finish. There is the boat in a ditch. 75% of its hull integrity has been breached and its remains are scattered on the ground."
  },
  {
    "key": "5-content",
    "original": "<……。>\n<CMT_KR>\n<CMT_JP>",
    "translation": "<……。>\n<CMT_KR>\n<CMT_JP>",
    "stage": 1,
    "context": "KR:\n&lt;…….&gt;\nEN:\n&lt;…….&gt;"
  },
  {
    "key": "6-content",
    "original": "わぁ、それならこれは舟の欠片みたいですね。\n<CMT_KR>\n<CMT_JP>",
    "translation": "わぁ、それならこれは舟の欠片みたいですね。\n<CMT_KR>\n<CMT_JP>",
    "stage": 1,
    "context": "KR:\n와, 그렇다면 이건 배에서부터 나온 조각인가 보네요.\nEN:\nWow, so this was a piece of our boat, huh?"
  },
  {
    "key": "7-content",
    "original": "…繰り返し利用することを考慮して作った舟だったのですが。\n<CMT_KR>\n<CMT_JP>",
    "translation": "…繰り返し利用することを考慮して作った舟だったのですが。\n<CMT_KR>\n<CMT_JP>",
    "stage": 1,
    "context": "KR:\n…다회 사용을 고려해서 만든 배였는데 말이죠.\nEN:\n... That vessel was designed to be used more than three times."
  },
  {
    "key": "8-content",
    "original": "ホンルが指さした場所には、可哀想に思えてくるくらい\n粉々になって転がっているプロペラが…。\n<CMT_KR>\n<CMT_JP>",
    "translation": "ホンルが指さした場所には、可哀想に思えてくるくらい\n粉々になって転がっているプロペラが…。\n<CMT_KR>\n<CMT_JP>",
    "stage": 1,
    "context": "KR:\n홍루가 가리킨 곳에는 불쌍할 정도로 조각조각 박살 나서 나뒹굴고 있는 프로펠러가…\nEN:\nHong Lu was pointing at the pitiful sight of an absolutely busted looking pieces of the propeller..."
  },
  {
    "key": "9-content",
    "original": "正確に言うと、一時は舟のエンジンであったはずの部品が\nガラガラと音を立てながら止まった。\n<CMT_KR>\n<CMT_JP>",
    "translation": "正確に言うと、一時は舟のエンジンであったはずの部品が\nガラガラと音を立てながら止まった。\n<CMT_KR>\n<CMT_JP>",
    "stage": 1,
    "context": "KR:\n정확히 말하자면, 한 때는 배의 엔진이었을 것 같은 부품이 털털 소리를 내며 멈춘다.\nEN:\n... Well, to be exact, busted pieces of the propeller and what appeared to once have been our boat's engines. Something comes to a sputtering halt amidst the wreckage."
  },
  {
    "key": "10-content",
    "original": "ついに息絶えけるや…。\n<CMT_KR>\n<CMT_JP>",
    "translation": "ついに息絶えけるや…。\n<CMT_KR>\n<CMT_JP>",
    "stage": 1,
    "context": "KR:\n기어이 숨을 거두는가…\nEN:\nThus it rests here forevermore..."
  },
  {
    "key": "11-content",
    "original": "この場面を見ば、ミカ嬢とレイン君の傷心なかなか酷からん。\n<CMT_KR>\n<CMT_JP>",
    "translation": "この場面を見ば、ミカ嬢とレイン君の傷心なかなか酷からん。\n<CMT_KR>\n<CMT_JP>",
    "stage": 1,
    "context": "KR:\n이 장면을 봤다면 미카 양하고 레인 군이 크게 상심했을 것이오.\nEN:\nThis would have been quite the painful sight for Mika and Rain."
  },
  {
    "key": "12-content",
    "original": "……。\n<CMT_KR>\n<CMT_JP>",
    "translation": "……。\n<CMT_KR>\n<CMT_JP>",
    "stage": 1,
    "context": "KR:\n…….\nEN:\n……."
  },
  {
    "key": "13-content",
    "original": "<一番傷心が酷いのは私たちだけどね…。>\n<CMT_KR>\n<CMT_JP>",
    "translation": "<一番傷心が酷いのは私たちだけどね…。>\n<CMT_KR>\n<CMT_JP>",
    "stage": 1,
    "context": "KR:\n&lt;제일 상심이 큰 건 우리긴 하지만…&gt;\nEN:\n&lt;... This is a pretty painful sight for us, too.&gt;"
  },
  {
    "key": "14-content",
    "original": "僕たち、これからどうすれば…。\n<CMT_KR>\n<CMT_JP>",
    "translation": "僕たち、これからどうすれば…。\n<CMT_KR>\n<CMT_JP>",
    "stage": 1,
    "context": "KR:\n저희, 이제 어떻게 해야…\nEN:\nUh, so... What do we..."
  },
  {
    "key": "15-content",
    "original": "管理人様、今も黄金の枝の位置は感じられてますよね。\n<CMT_KR>\n<CMT_JP>",
    "translation": "管理人様、今も黄金の枝の位置は感じられてますよね。\n<CMT_KR>\n<CMT_JP>",
    "stage": 1,
    "context": "KR:\n관리자님, 여전히 황금가지의 위치는 느껴지시죠.\nEN:\nManager. You can still sense the Golden Bough, right?"
  },
  {
    "key": "16-content",
    "original": "<うん、この前行った支部とは違うけど。確かに「この中」の\nどこかにはあるはず。でも遠いんだ、正確な方向までは…。>\n<CMT_KR>\n<CMT_JP>",
    "translation": "<うん、この前行った支部とは違うけど。確かに「この中」の\nどこかにはあるはず。でも遠いんだ、正確な方向までは…。>\n<CMT_KR>\n<CMT_JP>",
    "stage": 1,
    "context": "KR:\n&lt;응, 전에 갔던 지부 때랑은 달라. 분명히 ‘이 속’ 어딘가에는 있어. 그런데 멀어. 정확한 방향까지는…&gt;\nEN:\n&lt;Yeah. Unlike at the Lobotomy Corp. Branch, I can definitely feel that it's somewhere 'in here'. But it's also pretty far away, so I can't tell where it exactly—&gt;"
  },
  {
    "key": "17-content",
    "original": "…時計を巻き戻す準備はできていますか？\n<CMT_KR>\n<CMT_JP>",
    "translation": "…時計を巻き戻す準備はできていますか？\n<CMT_KR>\n<CMT_JP>",
    "stage": 1,
    "context": "KR:\n…시계를 돌릴 준비는 되어 있으시고요?\nEN:\n... Great. Are you ready to turn the clock?"
  },
  {
    "key": "18-content",
    "original": "<何で急に時計の話を…。>\n<CMT_KR>\n<CMT_JP>",
    "translation": "<何で急に時計の話を…。>\n<CMT_KR>\n<CMT_JP>",
    "stage": 1,
    "context": "KR:\n&lt;시계는 갑자기 왜…&gt;\nEN:\n&lt;What's that about turning the clock?&gt;"
  },
  {
    "key": "19-content",
    "original": "<あっ…。>\n<CMT_KR>\n<CMT_JP>",
    "translation": "<あっ…。>\n<CMT_KR>\n<CMT_JP>",
    "stage": 1,
    "context": "KR:\n&lt;아…&gt;\nEN:\n&lt;Ohh...&gt;"
  },
  {
    "key": "20-content",
    "original": "この鯨の影響を受けて、全身と精神が\n白く濁ったものに変貌してしまったものたち。\n<CMT_KR>\n<CMT_JP>",
    "translation": "この鯨の影響を受けて、全身と精神が\n白く濁ったものに変貌してしまったものたち。\n<CMT_KR>\n<CMT_JP>",
    "stage": 1,
    "context": "KR:\n이 고래의 영향을 받아 몸과 정신이 하얗고 탁하게 변해버린 것들.\nEN:\nThe Whale's pallor had taken over their bodies and minds."
  },
  {
    "key": "21-content",
    "original": "うん、当然ではあるけど\nここは…人魚でいっぱいだ。\n<CMT_KR>\n<CMT_JP>",
    "translation": "うん、当然ではあるけど\nここは…人魚でいっぱいだ。\n<CMT_KR>\n<CMT_JP>",
    "stage": 1,
    "context": "KR:\n그래, 당연하게도 이곳은… 인어들로 가득 차 있을 수 밖에.\nEN:\nOf course. It only makes sense that this place is crawling with Mermaids."
  }
]